{
  "version": "5.9.1",
  "flags": {},
  "shapes": [
    {
      "label": "RA",
      "points": [
        [
          335.6,
          338.0
        ],
        [
          307.6,
          349.20000000000005
        ],
        [
          283.6,
          383.6
        ],
        [
          286.0,
          422.0
        ],
        [
          279.6,
          462.8
        ],
        [
          282.8,
          498.8
        ],
        [
          298.8,
          524.4
        ],
        [
          318.0,
          545.2
        ],
        [
          363.6,
          565.2
        ],
        [
          386.8,
          570.8000000000001
        ],
        [
          410.8,
          574.0
        ],
        [
          419.6,
          566.8000000000001
        ],
        [
          426.0,
          529.2
        ],
        [
          426.0,
          504.40000000000003
        ],
        [
          420.40000000000003,
          472.40000000000003
        ],
        [
          422.8,
          438.8
        ],
        [
          431.6,
          409.20000000000005
        ],
        [
          431.6,
          354.0
        ],
        [
          419.6,
          338.8
        ],
        [
          374.0,
          329.20000000000005
        ]
      ],
      "group_id": null,
      "description": "",
      "shape_type": "polygon",
      "flags": {},
      "mask": null
    }
  ],
  "imagePath": "94331825_0048_frame35.png",
  "imageHeight": 708,
  "imageWidth": 1016,
  "bbox_prompt": [
    161,
    198,
    286,
    414
  ],
  "point_prompt": [
    230.70236220472444,
    311.07796610169487
  ],
  "image_size_for_box_and_point_prompt": [
    640,
    480
  ]
}