{
  "version": "5.9.1",
  "flags": {},
  "shapes": [
    {
      "label": "RA",
      "points": [
        [
          406.8,
          369.20000000000005
        ],
        [
          366.0,
          391.6
        ],
        [
          347.6,
          414.8
        ],
        [
          342.8,
          439.6
        ],
        [
          344.40000000000003,
          467.6
        ],
        [
          347.6,
          489.20000000000005
        ],
        [
          355.6,
          523.6
        ],
        [
          365.2,
          542.0
        ],
        [
          382.8,
          578.8000000000001
        ],
        [
          414.8,
          599.6
        ],
        [
          442.8,
          605.2
        ],
        [
          458.0,
          599.6
        ],
        [
          462.8,
          585.2
        ],
        [
          464.40000000000003,
          565.2
        ],
        [
          459.6,
          518.8000000000001
        ],
        [
          450.8,
          490.0
        ],
        [
          445.2,
          469.20000000000005
        ],
        [
          444.40000000000003,
          426.0
        ],
        [
          453.2,
          412.40000000000003
        ],
        [
          453.2,
          392.40000000000003
        ],
        [
          449.2,
          381.20000000000005
        ],
        [
          441.2,
          374.0
        ]
      ],
      "group_id": null,
      "description": "",
      "shape_type": "polygon",
      "flags": {},
      "mask": null
    }
  ],
  "imagePath": "95606436_0032_frame67.png",
  "imageHeight": 708,
  "imageWidth": 1016,
  "bbox_prompt": [
    204,
    226,
    304,
    434
  ],
  "point_prompt": [
    260.5125268432355,
    327.74114021571654
  ],
  "image_size_for_box_and_point_prompt": [
    640,
    480
  ]
}