{
  "version": "5.9.1",
  "flags": {},
  "shapes": [
    {
      "label": "RA",
      "points": [
        [
          378.0,
          331.6
        ],
        [
          353.2,
          346.8
        ],
        [
          330.0,
          367.6
        ],
        [
          323.6,
          397.20000000000005
        ],
        [
          326.8,
          430.8
        ],
        [
          332.40000000000003,
          445.20000000000005
        ],
        [
          347.6,
          466.0
        ],
        [
          368.40000000000003,
          480.40000000000003
        ],
        [
          390.8,
          490.8
        ],
        [
          411.6,
          494.0
        ],
        [
          434.8,
          494.0
        ],
        [
          452.40000000000003,
          484.40000000000003
        ],
        [
          462.8,
          470.8
        ],
        [
          466.0,
          452.40000000000003
        ],
        [
          466.8,
          444.40000000000003
        ],
        [
          467.6,
          426.0
        ],
        [
          467.6,
          406.0
        ],
        [
          469.2,
          381.20000000000005
        ],
        [
          468.40000000000003,
          355.6
        ],
        [
          448.40000000000003,
          334.8
        ],
        [
          419.6,
          325.20000000000005
        ],
        [
          407.6,
          326.0
        ]
      ],
      "group_id": null,
      "description": "",
      "shape_type": "polygon",
      "flags": {},
      "mask": null
    }
  ],
  "imagePath": "97680426_0032_frame16.png",
  "imageHeight": 708,
  "imageWidth": 1016,
  "bbox_prompt": [
    190,
    203,
    309,
    352
  ],
  "point_prompt": [
    257.5118110236221,
    282.0092449922958
  ],
  "image_size_for_box_and_point_prompt": [
    640,
    480
  ]
}