{
  "version": "5.9.1",
  "flags": {},
  "shapes": [
    {
      "label": "RA",
      "points": [
        [
          436.40000000000003,
          338.8
        ],
        [
          405.2,
          349.20000000000005
        ],
        [
          380.40000000000003,
          363.6
        ],
        [
          354.8,
          384.40000000000003
        ],
        [
          353.2,
          398.8
        ],
        [
          347.6,
          429.20000000000005
        ],
        [
          348.40000000000003,
          444.40000000000003
        ],
        [
          354.8,
          465.20000000000005
        ],
        [
          366.0,
          485.20000000000005
        ],
        [
          382.0,
          507.6
        ],
        [
          400.40000000000003,
          523.6
        ],
        [
          425.2,
          538.0
        ],
        [
          445.2,
          546.8000000000001
        ],
        [
          478.0,
          546.0
        ],
        [
          494.0,
          536.4
        ],
        [
          504.40000000000003,
          519.6
        ],
        [
          510.8,
          504.40000000000003
        ],
        [
          512.4,
          491.6
        ],
        [
          512.4,
          458.0
        ],
        [
          512.4,
          435.6
        ],
        [
          508.40000000000003,
          418.8
        ],
        [
          508.40000000000003,
          386.8
        ],
        [
          498.8,
          366.0
        ],
        [
          492.40000000000003,
          354.0
        ],
        [
          468.40000000000003,
          344.40000000000003
        ]
      ],
      "group_id": null,
      "description": "",
      "shape_type": "polygon",
      "flags": {},
      "mask": null
    }
  ],
  "imagePath": "97856480_0040_frame19.png",
  "imageHeight": 708,
  "imageWidth": 1016,
  "bbox_prompt": [
    203,
    208,
    338,
    391
  ],
  "point_prompt": [
    277.1754330708662,
    302.0040677966101
  ],
  "image_size_for_box_and_point_prompt": [
    640,
    480
  ]
}