{
  "version": "5.9.1",
  "flags": {},
  "shapes": [
    {
      "label": "LA",
      "points": [
        [
          542.8,
          348.40000000000003
        ],
        [
          510.00000000000006,
          356.40000000000003
        ],
        [
          474.8,
          404.40000000000003
        ],
        [
          459.6,
          434.8
        ],
        [
          458.0,
          467.6
        ],
        [
          458.8,
          480.40000000000003
        ],
        [
          461.2,
          505.20000000000005
        ],
        [
          466.8,
          521.2
        ],
        [
          510.8,
          538.0
        ],
        [
          518.8,
          536.4
        ],
        [
          533.1999999999999,
          534.8000000000001
        ],
        [
          558.0,
          534.8000000000001
        ],
        [
          572.4,
          536.4
        ],
        [
          582.0,
          532.4
        ],
        [
          584.4,
          527.6
        ],
        [
          596.4,
          487.6
        ],
        [
          598.0,
          467.6
        ],
        [
          598.0,
          446.8
        ],
        [
          598.0,
          400.40000000000003
        ],
        [
          598.0,
          386.0
        ],
        [
          598.0,
          374.8
        ],
        [
          598.0,
          367.6
        ]
      ],
      "group_id": null,
      "description": "",
      "shape_type": "polygon",
      "flags": {},
      "mask": null
    }
  ],
  "imagePath": "90705838_0100_frame45.png",
  "imageHeight": 708,
  "imageWidth": 1016,
  "bbox_prompt": [
    275,
    216,
    389,
    384
  ],
  "point_prompt": [
    340.0429491768074,
    314.0092449922959
  ],
  "image_size_for_box_and_point_prompt": [
    640,
    480
  ]
}