{
  "version": "5.9.1",
  "flags": {},
  "shapes": [
    {
      "label": "LA",
      "points": [
        [
          522.0,
          370.0
        ],
        [
          489.2,
          402.0
        ],
        [
          479.6,
          443.6
        ],
        [
          480.40000000000003,
          467.6
        ],
        [
          482.0,
          488.40000000000003
        ],
        [
          490.0,
          518.8000000000001
        ],
        [
          526.8,
          549.2
        ],
        [
          565.1999999999999,
          553.2
        ],
        [
          595.5999999999999,
          549.2
        ],
        [
          618.0,
          540.4
        ],
        [
          627.5999999999999,
          518.0
        ],
        [
          630.0,
          497.20000000000005
        ],
        [
          629.1999999999999,
          469.20000000000005
        ],
        [
          624.4,
          438.8
        ],
        [
          625.1999999999999,
          415.6
        ],
        [
          620.4,
          395.6
        ],
        [
          597.1999999999999,
          363.6
        ],
        [
          570.8,
          359.6
        ]
      ],
      "group_id": null,
      "description": "",
      "shape_type": "polygon",
      "flags": {},
      "mask": null
    }
  ],
  "imagePath": "94841827_0032_frame46.png",
  "imageHeight": 708,
  "imageWidth": 1016,
  "bbox_prompt": [
    287,
    224,
    411,
    394
  ],
  "point_prompt": [
    356.0314960629921,
    314.1242937853107
  ],
  "image_size_for_box_and_point_prompt": [
    640,
    480
  ]
}