{
  "version": "5.9.1",
  "flags": {},
  "shapes": [
    {
      "label": "LA",
      "points": [
        [
          489.2,
          422.0
        ],
        [
          470.0,
          448.40000000000003
        ],
        [
          457.2,
          472.40000000000003
        ],
        [
          449.2,
          505.20000000000005
        ],
        [
          446.0,
          538.8000000000001
        ],
        [
          448.40000000000003,
          560.4
        ],
        [
          470.0,
          596.4
        ],
        [
          485.2,
          602.8000000000001
        ],
        [
          513.1999999999999,
          605.2
        ],
        [
          536.4,
          587.6
        ],
        [
          558.0,
          562.8000000000001
        ],
        [
          559.5999999999999,
          534.8000000000001
        ],
        [
          562.8,
          514.8000000000001
        ],
        [
          567.5999999999999,
          485.20000000000005
        ],
        [
          570.0,
          475.6
        ],
        [
          562.0,
          436.40000000000003
        ],
        [
          539.5999999999999,
          418.0
        ]
      ],
      "group_id": null,
      "description": "",
      "shape_type": "polygon",
      "flags": {},
      "mask": null
    }
  ],
  "imagePath": "95660564_0032_frame74.png",
  "imageHeight": 708,
  "imageWidth": 1016,
  "bbox_prompt": [
    269,
    264,
    370,
    429
  ],
  "point_prompt": [
    321.79342288096336,
    349.62313060817553
  ],
  "image_size_for_box_and_point_prompt": [
    640,
    480
  ]
}