{
  "version": "5.9.1",
  "flags": {},
  "shapes": [
    {
      "label": "LA",
      "points": [
        [
          492.40000000000003,
          394.8
        ],
        [
          476.40000000000003,
          416.40000000000003
        ],
        [
          437.2,
          438.0
        ],
        [
          414.0,
          454.0
        ],
        [
          406.8,
          478.0
        ],
        [
          403.6,
          493.20000000000005
        ],
        [
          406.0,
          524.4
        ],
        [
          420.40000000000003,
          542.8000000000001
        ],
        [
          447.6,
          570.0
        ],
        [
          464.40000000000003,
          580.4
        ],
        [
          488.40000000000003,
          585.2
        ],
        [
          510.8,
          586.0
        ],
        [
          523.5999999999999,
          577.2
        ],
        [
          537.1999999999999,
          560.4
        ],
        [
          544.4,
          545.2
        ],
        [
          553.1999999999999,
          525.2
        ],
        [
          573.1999999999999,
          510.0
        ],
        [
          583.5999999999999,
          500.40000000000003
        ],
        [
          588.4,
          493.20000000000005
        ],
        [
          594.8,
          478.8
        ],
        [
          597.1999999999999,
          468.40000000000003
        ],
        [
          597.1999999999999,
          456.40000000000003
        ],
        [
          594.0,
          439.6
        ],
        [
          590.8,
          429.20000000000005
        ],
        [
          577.1999999999999,
          414.0
        ],
        [
          569.1999999999999,
          403.6
        ],
        [
          524.4,
          388.40000000000003
        ]
      ],
      "group_id": null,
      "description": "",
      "shape_type": "polygon",
      "flags": {},
      "mask": null
    }
  ],
  "imagePath": "97010008_0022_frame14.png",
  "imageHeight": 708,
  "imageWidth": 1016,
  "bbox_prompt": [
    235,
    243,
    394,
    417
  ],
  "point_prompt": [
    324.67541557305333,
    332.7859384808537
  ],
  "image_size_for_box_and_point_prompt": [
    640,
    480
  ]
}